lastapi/__init__.py
lastapi/core.py
lastapi/helper.py
lastapi/schemas/cloudflare.yaml
lastapi/schemas/httpbin-params.yaml
lastapi/schemas/httpbin.yaml
lastapi/schemas/schema.yaml
lastapi-0.2.data/scripts/lapi
lastapi-0.2.dist-info/LICENSE
lastapi-0.2.dist-info/METADATA
lastapi-0.2.dist-info/WHEEL
lastapi-0.2.dist-info/top_level.txt
lastapi-0.2.dist-info/RECORD
