Metadata-Version: 2.1
Name: lastapi
Version: 0.2
Summary: REST API defined as YAML and invoked with lastapi.
Home-page: https://github.com/raynix/lastapi
Author: raynix
Author-email: raynix@gmail.com
License: UNKNOWN
Platform: UNKNOWN
Classifier: Programming Language :: Python :: 3.7
Classifier: License :: OSI Approved :: GNU General Public License v3 (GPLv3)
Classifier: Intended Audience :: Developers
Classifier: Intended Audience :: System Administrators
Classifier: Operating System :: OS Independent
